courtana/__init__.py
courtana/annotations.py
courtana/experiment.py
courtana/jaaba.py
courtana/video.py
courtana/tools/__init__.py
courtana/tools/colorline.py
courtana/tools/oneeurofilter.py
courtana/tracker/__init__.py
courtana/tracker/doctor.py
courtana/tracker/flytracker.py
courtana/tracker/opencsp.py
courtana/tracker/trackdata.py
courtana-0.7.1.data/data/CONTRIBUTING.rst
courtana-0.7.1.data/data/DESCRIPTION.rst
courtana-0.7.1.data/data/LICENSE
courtana-0.7.1.dist-info/DESCRIPTION.rst
courtana-0.7.1.dist-info/METADATA
courtana-0.7.1.dist-info/RECORD
courtana-0.7.1.dist-info/WHEEL
courtana-0.7.1.dist-info/metadata.json
courtana-0.7.1.dist-info/top_level.txt
