Metadata-Version: 2.0
Name: courtana
Version: 0.7.1
Summary: Tools for courtship analysis
Home-page: https://bitbucket.org/fchampalimaud/courtana
Author: Hugo Cachitas
Author-email: hugo.cachitas@neuro.fchampalimaud.org
License: BSD
Platform: UNKNOWN
Classifier: Development Status :: 3 - Alpha
Classifier: Intended Audience :: Developers
Classifier: License :: OSI Approved :: BSD License
Classifier: Operating System :: Unix
Classifier: Operating System :: POSIX
Classifier: Operating System :: Microsoft :: Windows
Classifier: Programming Language :: Python :: 3
Classifier: Programming Language :: Python :: 3.5
Classifier: Programming Language :: Python :: 3.6
Classifier: Topic :: Utilities
Requires-Dist: numpy
Requires-Dist: pandas (==0.19.2)
Requires-Dist: numexpr
Requires-Dist: scipy
Requires-Dist: tables
Requires-Dist: matplotlib
